setup.py
distributions_tfrance/Binomialdistribution.py
distributions_tfrance/Gaussiandistribution.py
distributions_tfrance/Generaldistribution.py
distributions_tfrance/__init__.py
distributions_tfrance.egg-info/PKG-INFO
distributions_tfrance.egg-info/SOURCES.txt
distributions_tfrance.egg-info/dependency_links.txt
distributions_tfrance.egg-info/not-zip-safe
distributions_tfrance.egg-info/top_level.txt